cfg_cli/__init__.py
cfg_cli/clients/api.py
cfg_cli/clients/db.py
cfg_cli/clients/s3.py
cfg_cli/config.py
cfg_cli/errors/error_handling.py
cfg_cli/errors/exceptions.py
cfg_cli/prism_cli.py
cfg_cli/utils.py
cfg_cli-0.1.32.dist-info/entry_points.txt
cfg_cli-0.1.32.dist-info/WHEEL
cfg_cli-0.1.32.dist-info/METADATA
cfg_cli-0.1.32.dist-info/RECORD
